hticoding/__init__.py
hticoding/hticoding.py
hticoding-0.1.dist-info/METADATA
hticoding-0.1.dist-info/WHEEL
hticoding-0.1.dist-info/top_level.txt
hticoding-0.1.dist-info/RECORD
