Metadata-Version: 2.1
Name: hticoding
Version: 0.1
Summary: Python functions for controlling Arduino devices
Author: taein
Author-email: hti7220@gmail.com
Requires-Dist: pyserial
